cloudimage/__init__.py
cloudimage/admin.py
cloudimage/apps.py
cloudimage/models.py
cloudimage/tests.py
cloudimage/urls.py
cloudimage/views.py
cloudimage/migrations/__init__.py
cloudimage/templatetags/__init__.py
cloudimage/templatetags/cloudimage.py
django_cloudimage-1.0.1.dist-info/DESCRIPTION.rst
django_cloudimage-1.0.1.dist-info/METADATA
django_cloudimage-1.0.1.dist-info/RECORD
django_cloudimage-1.0.1.dist-info/WHEEL
django_cloudimage-1.0.1.dist-info/metadata.json
django_cloudimage-1.0.1.dist-info/top_level.txt
django_cloudimage-1.0.1.dist-info/zip-safe
